pysmartmeter/__init__.py
pysmartmeter/__main__.py
pysmartmeter/constants.py
pysmartmeter/data_classes.py
pysmartmeter/detect_serial.py
pysmartmeter/mqtt_handler.py
pysmartmeter/mqtt_publish.py
pysmartmeter/obis2ha_sensors.py
pysmartmeter/parser.py
pysmartmeter/user_settings.py
pysmartmeter/cli_app/__init__.py
pysmartmeter/cli_app/debug.py
pysmartmeter/cli_app/mqtt.py
pysmartmeter/cli_app/settings.py
pysmartmeter/cli_app/systemd.py
pysmartmeter/cli_dev/__init__.py
pysmartmeter/cli_dev/code_style.py
pysmartmeter/cli_dev/packaging.py
pysmartmeter/cli_dev/settings.py
pysmartmeter/cli_dev/testing.py
pysmartmeter/cli_dev/update_readme_history.py
pysmartmeter/definitions/ebz_dd3.toml
pysmartmeter/tests/__init__.py
pysmartmeter/tests/base.py
pysmartmeter/tests/data.py
pysmartmeter/tests/mocks.py
pysmartmeter/tests/test_definitions.py
pysmartmeter/tests/test_doctests.py
pysmartmeter/tests/test_mqtt_publish.py
pysmartmeter/tests/test_mqtt_publish_publish_forever_config_payload_1.snapshot.json
pysmartmeter/tests/test_mqtt_publish_publish_forever_state_messages_1.snapshot.json
pysmartmeter/tests/test_obis2ha_sensor.py
pysmartmeter/tests/test_parser.py
pysmartmeter/tests/test_parser_handle_empty_line_1.snapshot.json
pysmartmeter/tests/test_parser_happy_path_1.snapshot.json
pysmartmeter/tests/test_parser_interim_incorrect_data_1.snapshot.json
pysmartmeter/tests/test_parser_start_in_the_middle_1.snapshot.json
pysmartmeter/tests/test_project_setup.py
pysmartmeter/tests/test_readme.py
pysmartmeter/tests/test_readme_history.py
pysmartmeter/tests/test_user_settings.py
pysmartmeter/tests/test_user_settings_hichi_dataclass_1.snapshot.json
pysmartmeter/utilities/serializer.py
pysmartmeter-0.7.0.dist-info/METADATA
pysmartmeter-0.7.0.dist-info/WHEEL
pysmartmeter-0.7.0.dist-info/entry_points.txt
pysmartmeter-0.7.0.dist-info/licenses/LICENSE
pysmartmeter-0.7.0.dist-info/RECORD
