Metadata-Version: 2.4
Name: pysmartmeter
Version: 0.7.0
Summary: Collect data from Hichi Smartmeter and expose it via MQTT
Project-URL: Documentation, https://github.com/jedie/pysmartmeter
Project-URL: Source, https://github.com/jedie/pysmartmeter
Author-email: Jens Diemer <pysmartmeter@jensdiemer.de>
License: GPL-3.0-or-later
License-File: LICENSE
Requires-Python: >=3.11
Requires-Dist: bx-py-utils
Requires-Dist: cli-base-utilities
Requires-Dist: cli-base-utilities>=0.17.0
Requires-Dist: ha-services>=2.15.0
Requires-Dist: paho-mqtt
Requires-Dist: pyserial
Requires-Dist: rich
Requires-Dist: tyro
